AUTHORS.rst
CHANGELOG.rst
LICENSE
MANIFEST.in
README.rst
setup.py
jmbo_music.egg-info/PKG-INFO
jmbo_music.egg-info/SOURCES.txt
jmbo_music.egg-info/dependency_links.txt
jmbo_music.egg-info/not-zip-safe
jmbo_music.egg-info/requires.txt
jmbo_music.egg-info/top_level.txt
music/__init__.py
music/admin.py
music/api.py
music/generator.py
music/models.py
music/urls.py
music/utils.py
music/management/__init__.py
music/management/__init__.pyc
music/management/commands/__init__.py
music/management/commands/__init__.pyc
music/management/commands/base_track_feed.py
music/management/commands/base_track_feed.pyc
music/management/commands/track_feed_example.py
music/management/commands/track_feed_example.pyc
music/migrations/0001_initial.py
music/migrations/0001_initial.pyc
music/migrations/0002_auto__add_field_track_audio_embed.py
music/migrations/0002_auto__add_field_track_audio_embed.pyc
music/migrations/0003_auto__add_field_musiccreditoption_role_type.py
music/migrations/0003_auto__add_field_musiccreditoption_role_type.pyc
music/migrations/0004_auto__del_musiccreditoption__add_creditoption__del_field_credit_role__.py
music/migrations/0004_auto__del_musiccreditoption__add_creditoption__del_field_credit_role__.pyc
music/migrations/0005_auto__chg_field_credit_credit_option__add_index_track_last_played.py
music/migrations/0005_auto__chg_field_credit_credit_option__add_index_track_last_played.pyc
music/migrations/__init__.py
music/migrations/__init__.pyc
music/static/basic/music/images/default.png
music/templates/basic/music/inclusion_tags/audioembed_detail.html
music/templates/basic/music/inclusion_tags/track_detail.html
music/templates/web/music/inclusion_tags/track_detail.html
music/tests/__init__.py
music/tests/urls.py